README.md
setup.py
meanfield/Anisotropy.py
meanfield/DMI.py
meanfield/EnergyTerm.py
meanfield/Exchange.py
meanfield/Math.py
meanfield/Zeeman.py
meanfield/__init__.py
meanfield/meanField.py
meanfield.egg-info/PKG-INFO
meanfield.egg-info/SOURCES.txt
meanfield.egg-info/dependency_links.txt
meanfield.egg-info/top_level.txt
test/test_all.py