Metadata-Version: 2.1
Name: meanfield
Version: 0.4.0
Summary: mean-field model
Author: xy721
Author-email: yxy332211@gmail.com
License: MIT-0
Keywords: pip,pathtool,timetool,magetool,mage
Platform: any
